scrapingtools/__init__.py
scrapingtools/utils/__init__.py
scrapingtools/utils/product_counter.py
scrapingtools/utils/transform.py
byprice_scrapingtools-0.0.9.dist-info/LICENSE
byprice_scrapingtools-0.0.9.dist-info/METADATA
byprice_scrapingtools-0.0.9.dist-info/WHEEL
byprice_scrapingtools-0.0.9.dist-info/top_level.txt
byprice_scrapingtools-0.0.9.dist-info/RECORD
