Metadata-Version: 2.1
Name: byprice-scrapingtools
Version: 0.0.9
Summary: Useful tools to scrape online stores
Home-page: https://github.com/ByPrice/scraping-tools
Author: Oswaldo Cruz Simon
Author-email: oswaldo@byprice.com
License: MIT
Keywords: scraping,ByPrice,Counter by hierarchy
Platform: UNKNOWN
Requires-Dist: redis (>=3.3.8)
